LICENSE_GPL.TXT
MANIFEST.in
README.md
RELEASE_NOTES.TXT
setup.py
mmfinder/__init__.py
mmfinder/mmfinder.py
mmfinder/mmfinder_config.py
mmfinder/mmfinder_deamon.py
mmfinder.egg-info/PKG-INFO
mmfinder.egg-info/SOURCES.txt
mmfinder.egg-info/dependency_links.txt
mmfinder.egg-info/entry_points.txt
mmfinder.egg-info/requires.txt
mmfinder.egg-info/top_level.txt
mmfinder/lib/__init__.py
mmfinder/lib/utils.py