Metadata-Version: 1.0
Name: mmfinder
Version: 0.98.alpha
Summary: a tool for finding your files across different machines
Home-page: https://github.com/m4rx9/mmfinder
Author: Marcin Magnus
Author-email: mag_dex@o2.pl
License: GPLv3
Platform: UNKNOWN
